{
  "Fish" : {
    "Fillet or Pieces Smoked" : [ {
      "name" : "Regular or Lox",
      "price" : "$3.75 per lb"
    }, {
      "name" : "Regular Pepper",
      "price" : "$3.95 per lb"
    }, {
      "name" : "Honey Flavor",
      "price" : "$4.49 per lb"
    }, {
      "name" : "Honey Pepper",
      "price" : "$4.95 per lb"
    }, {
      "name" : "Honey Chili Garlic",
      "price" : "$4.95 per lb"
    }, {
      "name" : "Teriyaki Flavor",
      "price" : "$4.95 per lb"
    }, {
      "name" : "Teriyaki Pepper",
      "price" : "$4.95 per lb"
    }, {
      "name" : "Teriyaki Chili Garlic",
      "price" : "$5.49 per lb"
    } ],
    "Fresh Fish Filleting or Steaking" : [ {
      "name" : "0 to 7 lbs",
      "price" : "$9.95 per fish"
    }, {
      "name" : "7 to 15 lbs",
      "price" : "$11.95 per fish"
    }, {
      "name" : "15 to 25 lbs",
      "price" : "$15.95 per fish"
    }, {
      "name" : "Over 25 lbs",
      "price" : "$19.95 per fish"
    } ],
    "Smoked Trout (under 14 inches)" : [ {
      "name" : "Regular",
      "price" : "$6.95 each"
    }, {
      "name" : "Honey Flavor",
      "price" : "$7.95 each"
    }, {
      "name" : "Honey Chili Garlic",
      "price" : "$8.25 each"
    }, {
      "name" : "Teriyaki Flavor",
      "price" : "$7.95 each"
    }, {
      "name" : "Pepper Added",
      "price" : "$2.00 each"
    }, {
      "name" : "Cleaning Charge",
      "price" : "$2.50 each"
    } ],
    "Smoked Trout (under 20 inches)" : [ {
      "name" : "Regular",
      "price" : "$7.95 each"
    }, {
      "name" : "Honey Flavor",
      "price" : "$9.95 each"
    }, {
      "name" : "Honey Chili Garlic",
      "price" : "$10.25 each"
    }, {
      "name" : "Teriyaki Flavor",
      "price" : "$9.95 each"
    }, {
      "name" : "Pepper Added",
      "price" : "$2.00 each"
    }, {
      "name" : "Cleaning Charge",
      "price" : "$2.50 each"
    } ],
    "Vacuum Packing" : [ {
      "name" : "Small",
      "price" : "$0.85 ea"
    }, {
      "name" : "Large",
      "price" : "$2.00 ea"
    } ],
    "Whole Fish Smoked" : [ {
      "name" : "Regular or Lox",
      "price" : "$2.95 per lb"
    }, {
      "name" : "Regular Pepper",
      "price" : "$3.50 per lb"
    }, {
      "name" : "Honey Flavor",
      "price" : "$3.75 per lb"
    }, {
      "name" : "Honey Pepper",
      "price" : "$3.95 per lb"
    }, {
      "name" : "Honey Chili Garlic",
      "price" : "$4.49 per lb"
    }, {
      "name" : "Teriyaki Flavor",
      "price" : "$3.95 per lb"
    }, {
      "name" : "Teriyaki Pepper",
      "price" : "$3.95 per lb"
    }, {
      "name" : "Teriyaki Chili Garlic",
      "price" : "$4.49 per lb"
    } ]
  }
}

